<?xml version="1.0" encoding="utf-8"?>
<language>
	<voice>
		<id>Prueba</id>
		<resource-path>prueba</resource-path>
	</voice>
	<text>
		<id>ExitConfirmationMenuCancelButton</id>
		<value>Cancelar</value>
	</text>
	<text>
		<id>ExitConfirmationMenuExitButton</id>
		<value>Salir</value>
	</text>
	<text>
		<id>GoBackConfirmationMenuCancelButton</id>
		<value>Cancelar</value>
	</text>
	<text>
		<id>GoBackConfirmationMenuGoBackButton</id>
		<value>Aceptar</value>
	</text>
	<text>
		<id>LoadGameMenuCancelButton</id>
		<value>Cancelar</value>
	</text>
	<text>
		<id>MainMenuExitButton</id>
		<value>Salir</value>
	</text>
	<text>
		<id>MainMenuLoadGameButton</id>
		<value>Cargar partida</value>
	</text>
	<text>
		<id>MainMenuNewGameButton</id>
		<value>Nueva partida</value>
	</text>
	<text>
		<id>MainMenuOptionsButton</id>
		<value>Opciones</value>
	</text>
	<text>
		<id>OptionsMenuApplyChangesButton</id>
		<value>Aplicar cambios</value>
	</text>
	<text>
		<id>OptionsMenuCancelButton</id>
		<value>Cancelar</value>
	</text>
	<text>
		<id>PauseMenuGoBackButton</id>
		<value>Volver al menu principal</value>
	</text>
	<text>
		<id>PauseMenuResumeGameButton</id>
		<value>Reanudar partida</value>
	</text>
	<text>
		<id>PauseMenuSaveGameButton</id>
		<value>Guardar partida</value>
	</text>
	<text>
		<id>SaveGameMenuCancelButton</id>
		<value>Cancelar</value>
	</text>
	<text>
		<id>SaveGameMenuNewStateIdButton</id>
		<value>Nueva partida</value>
	</text>
	<text>
		<id>SaveGameMenuNewStateIdTextField</id>
		<value>Nombre de la partida</value>
	</text>
	<text>
		<id>SaveGameMenuSaveGameButton</id>
		<value>Guardar partida</value>
	</text>
</language>